pySmartDL/__init__.py
pySmartDL/control_thread.py
pySmartDL/download.py
pySmartDL/pySmartDL.py
pySmartDL/utils.py
test/__init__.py
test/test_pySmartDL.py
pySmartDL-1.3.3.dist-info/LICENSE.txt
pySmartDL-1.3.3.dist-info/METADATA
pySmartDL-1.3.3.dist-info/WHEEL
pySmartDL-1.3.3.dist-info/top_level.txt
pySmartDL-1.3.3.dist-info/RECORD
